onebot/__init__.py
onebot/application.py
onebot/exceptions.py
onebot/dtypes/__init__.py
onebot/dtypes/enum.py
onebot/dtypes/message.py
onebot/dtypes/models.py
onebot/fliters/__init__.py
onebot/fliters/interfaces.py
onebot/fliters/impl/__init__.py
onebot/fliters/impl/group.py
onebot/fliters/impl/message.py
onebot/handlers/__init__.py
onebot/handlers/composite.py
onebot/handlers/interfaces.py
onebot/handlers/registration.py
onebot/handlers/impl/__init__.py
onebot/handlers/impl/echo.py
onebot/handlers/impl/message.py
onebot/handlers/impl/meta.py
onebot/handlers/impl/request.py
onebot/parameter/__init__.py
onebot/parameter/arguments.py
onebot/parameter/composite.py
onebot/parameter/interfaces.py
onebot/parameter/resolver/__init__.py
onebot/parameter/resolver/app.py
onebot/parameter/resolver/depends.py
llonebot-1.0.3.dist-info/METADATA
llonebot-1.0.3.dist-info/WHEEL
llonebot-1.0.3.dist-info/top_level.txt
llonebot-1.0.3.dist-info/RECORD
