Metadata-Version: 2.1
Name: llonebot
Version: 1.0.3
Summary: NTQQ llonebot插件 python交互包
Home-page: https://github.com/z719893361/llonebot
Author: 格索伊
Author-email: 719893361@qq.com
Project-URL: Bug Tracker, https://github.com/z719893361/llonebot/issues
Requires-Python: >=3.7
Requires-Dist: websockets
Requires-Dist: pydantic
Requires-Dist: aiocron
